PySubtrans/Instructions.py
PySubtrans/Options.py
PySubtrans/ProviderSettingsView.py
PySubtrans/SettingsType.py
PySubtrans/Substitutions.py
PySubtrans/SubtitleBatch.py
PySubtrans/SubtitleBatcher.py
PySubtrans/SubtitleBuilder.py
PySubtrans/SubtitleData.py
PySubtrans/SubtitleEditor.py
PySubtrans/SubtitleError.py
PySubtrans/SubtitleFileHandler.py
PySubtrans/SubtitleFormatRegistry.py
PySubtrans/SubtitleLine.py
PySubtrans/SubtitleProcessor.py
PySubtrans/SubtitleProject.py
PySubtrans/SubtitleScene.py
PySubtrans/SubtitleSerialisation.py
PySubtrans/SubtitleTranslator.py
PySubtrans/SubtitleValidator.py
PySubtrans/Subtitles.py
PySubtrans/Translation.py
PySubtrans/TranslationClient.py
PySubtrans/TranslationEvents.py
PySubtrans/TranslationParser.py
PySubtrans/TranslationPrompt.py
PySubtrans/TranslationProvider.py
PySubtrans/TranslationRequest.py
PySubtrans/VersionCheck.py
PySubtrans/__init__.py
PySubtrans/version.py
PySubtrans/Formats/SSAFileHandler.py
PySubtrans/Formats/SrtFileHandler.py
PySubtrans/Formats/VttFileHandler.py
PySubtrans/Formats/__init__.py
PySubtrans/Helpers/Color.py
PySubtrans/Helpers/ContextHelpers.py
PySubtrans/Helpers/InstructionsHelpers.py
PySubtrans/Helpers/Localization.py
PySubtrans/Helpers/Parse.py
PySubtrans/Helpers/Resources.py
PySubtrans/Helpers/SubtitleHelpers.py
PySubtrans/Helpers/TestCases.py
PySubtrans/Helpers/Tests.py
PySubtrans/Helpers/Text.py
PySubtrans/Helpers/Time.py
PySubtrans/Helpers/Version.py
PySubtrans/Helpers/__init__.py
PySubtrans/Providers/Provider_Azure.py
PySubtrans/Providers/Provider_Bedrock.py
PySubtrans/Providers/Provider_Claude.py
PySubtrans/Providers/Provider_Custom.py
PySubtrans/Providers/Provider_DeepSeek.py
PySubtrans/Providers/Provider_Gemini.py
PySubtrans/Providers/Provider_Mistral.py
PySubtrans/Providers/Provider_OpenAI.py
PySubtrans/Providers/Provider_OpenRouter.py
PySubtrans/Providers/__init__.py
PySubtrans/Providers/Clients/AnthropicClient.py
PySubtrans/Providers/Clients/AzureOpenAIClient.py
pysubtrans-1.5.6.dist-info/licenses/LICENSE
pysubtrans-1.5.6.dist-info/METADATA
pysubtrans-1.5.6.dist-info/WHEEL
pysubtrans-1.5.6.dist-info/top_level.txt
pysubtrans-1.5.6.dist-info/RECORD
