Metadata-Version: 2.4
Name: pysubtrans
Version: 1.5.6
Summary: Core subtitle translation toolkit used by LLM-Subtrans
License-Expression: MIT
Project-URL: Homepage, https://github.com/machinewrapped/llm-subtrans
Project-URL: Documentation, https://github.com/machinewrapped/llm-subtrans/blob/main/PySubtrans/README.md
Project-URL: Source, https://github.com/machinewrapped/llm-subtrans
Project-URL: Issues, https://github.com/machinewrapped/llm-subtrans/issues
Requires-Python: >=3.10
License-File: LICENSE
Requires-Dist: python-dotenv
Requires-Dist: srt
Requires-Dist: pysubs2
Requires-Dist: regex
Requires-Dist: babel
Requires-Dist: appdirs
Requires-Dist: blinker
Requires-Dist: requests
Requires-Dist: setuptools
Requires-Dist: httpx
Requires-Dist: httpx[socks]
Provides-Extra: openai
Requires-Dist: openai; extra == "openai"
Provides-Extra: azure
Requires-Dist: openai; extra == "azure"
Provides-Extra: gemini
Requires-Dist: google-genai; extra == "gemini"
Requires-Dist: google-api-core; extra == "gemini"
Provides-Extra: claude
Requires-Dist: anthropic; extra == "claude"
Provides-Extra: mistral
Requires-Dist: mistralai; extra == "mistral"
Provides-Extra: bedrock
Requires-Dist: boto3; extra == "bedrock"
Dynamic: license-file
